pygame_textinput/__init__.py
pygame_textinput/pygame_textinput.py
pygame_textinput-1.0.1.dist-info/LICENSE
pygame_textinput-1.0.1.dist-info/METADATA
pygame_textinput-1.0.1.dist-info/WHEEL
pygame_textinput-1.0.1.dist-info/top_level.txt
pygame_textinput-1.0.1.dist-info/RECORD
