Metadata-Version: 2.1
Name: pygame-textinput
Version: 1.0.1
Summary: Enter text using pygame
Home-page: https://github.com/Nearoo/pygame-text-input
Author: Silas Gyger
Author-email: silasgyger@gmail.com
License: MIT
Platform: UNKNOWN
Classifier: License :: OSI Approved :: MIT License
Classifier: Programming Language :: Python :: 3
Classifier: Programming Language :: Python :: 3.7
License-File: LICENSE
